profile_binr/__init__.py
profile_binr/_R/PROFILE_source.R
profile_binr/wrappers/__init__.py
profile_binr/wrappers/probinr.py
profile_binr-0.1.2.dist-info/LICENSE
profile_binr-0.1.2.dist-info/METADATA
profile_binr-0.1.2.dist-info/WHEEL
profile_binr-0.1.2.dist-info/top_level.txt
profile_binr-0.1.2.dist-info/RECORD
