Metadata-Version: 2.1
Name: profile-binr
Version: 0.1.2
Summary: PROFILE methodology for the binarisation and normalisation of RNA-seq data
Home-page: https://github.com/bnediction/profile_binr
Author: Gustavo Magaña López
Author-email: gustavo.magana-lopez@u-psud.fr
License: BSD-3
Platform: UNKNOWN
Classifier: Intended Audience :: Science/Research
Classifier: Topic :: Scientific/Engineering
Classifier: Topic :: Scientific/Engineering :: Bio-Informatics
Requires-Dist: pandas
Requires-Dist: rpy2
